keyspwgenerator/__init__.py
keyspwgenerator/cli.py
keyspwgenerator/tools.py
keyspwgenerator-0.1.0.dist-info/LICENSE
keyspwgenerator-0.1.0.dist-info/WHEEL
keyspwgenerator-0.1.0.dist-info/entry_points.txt
keyspwgenerator-0.1.0.dist-info/METADATA
keyspwgenerator-0.1.0.dist-info/RECORD
