Metadata-Version: 2.1
Name: keyspwgenerator
Version: 0.1.0
Summary: CLI tool that creates passwords
Home-page: https://github.com/jsattari/keys-pw-generator
License: MIT
Keywords: keyspwgenerator,password,generator
Author: John Sattari
Author-email: jsattari3@gmail.com
Requires-Python: >=3.8,<4.0
Classifier: License :: OSI Approved :: MIT License
Classifier: Programming Language :: Python :: 3
Classifier: Programming Language :: Python :: 3.8
Classifier: Programming Language :: Python :: 3.9
Classifier: Programming Language :: Python :: 3.10
Classifier: Programming Language :: Python :: 3.11
Requires-Dist: click (>=8.1.3,<9.0.0)
Project-URL: Repository, https://github.com/jsattari/keys-pw-generator
